pyhcl2/__init__.py
pyhcl2/eval.py
pyhcl2/generations.py
pyhcl2/hcl2.lark
pyhcl2/models.py
pyhcl2/nodes.py
pyhcl2/parse.py
pyhcl2/py.typed
pyhcl2/repl.py
pyhcl2/rich_utils.py
pyhcl2/tracker.py
pyhcl2/transformer.py
pyhcl2/values.py
pyhcl2-2.0.0.dist-info/METADATA
pyhcl2-2.0.0.dist-info/WHEEL
pyhcl2-2.0.0.dist-info/entry_points.txt
pyhcl2-2.0.0.dist-info/licenses/LICENSE
pyhcl2-2.0.0.dist-info/RECORD
