Metadata-Version: 2.4
Name: pyhcl2
Version: 2.0.0
Summary: 
License: MIT
License-File: LICENSE
Author: RISQ Capital
Author-email: dev@risqcapital.com
Requires-Python: >=3.11, !=2.7.*, !=3.0.*, !=3.1.*, !=3.2.*, !=3.3.*, !=3.4.*, !=3.5.*, !=3.6.*, !=3.7.*, !=3.8.*, !=3.9.*, !=3.10.*
Classifier: License :: OSI Approved :: MIT License
Classifier: Programming Language :: Python :: 3
Classifier: Programming Language :: Python :: 3.11
Classifier: Programming Language :: Python :: 3.12
Classifier: Programming Language :: Python :: 3.13
Classifier: Programming Language :: Python :: 3.14
Provides-Extra: repl
Requires-Dist: lark (>=1.3.1,<2.0.0)
Requires-Dist: networkx (>=3.6.1,<4.0.0)
Requires-Dist: prompt-toolkit (>=2.0.1,<4.0.0) ; extra == "repl"
Requires-Dist: pyagnostics (>=3.0.0,<4.0.0)
Requires-Dist: pydantic (>=2.12.5,<3.0.0)
Requires-Dist: rich (>=14.2.0,<15.0.0)
Requires-Dist: termcolor (>=3.3.0,<4.0.0)
Project-URL: Bug Tracker, https://github.com/risqcapital/pyhcl2/issues
Project-URL: Repository, https://github.com/risqcapital/pyhcl2
